ayush_py/__init__.py
ayush_py/first.py
ayush_py-0.1.8.dist-info/LICENSE
ayush_py-0.1.8.dist-info/METADATA
ayush_py-0.1.8.dist-info/WHEEL
ayush_py-0.1.8.dist-info/top_level.txt
ayush_py-0.1.8.dist-info/RECORD
