Metadata-Version: 2.1
Name: ayush_py
Version: 0.1.8
Summary: A simple Python package for greeting people.
Home-page: https://github.com/yourusername/mypackage
Author: Ayush Mehrotra
Author-email: ayush.mehrotra900@gmail.com
Classifier: Programming Language :: Python :: 3
Classifier: License :: OSI Approved :: MIT License
Classifier: Operating System :: OS Independent
License-File: LICENSE
